symptom_analysis/__init__.py
symptom_analysis/analyzer.py
symptom_analysis/data.py
symptom_analysis-1.0.0.dist-info/METADATA
symptom_analysis-1.0.0.dist-info/WHEEL
symptom_analysis-1.0.0.dist-info/top_level.txt
symptom_analysis-1.0.0.dist-info/RECORD
