Metadata-Version: 2.2
Name: symptom_analysis
Version: 1.0.0
Summary: A custom Python library for symptom analysis
Home-page: https://github.com/Yashashwini0310/cpp_project
Author: YashashwiniS
Author-email: Yashashwini222@gmail.com
Classifier: Programming Language :: Python :: 3
Classifier: License :: OSI Approved :: MIT License
Classifier: Operating System :: OS Independent
Requires-Python: >=3.6
Dynamic: author
Dynamic: author-email
Dynamic: classifier
Dynamic: description
Dynamic: description-content-type
Dynamic: home-page
Dynamic: requires-python
Dynamic: summary
